Workbook

Sheet 測試資料集
A1: 編號 | B1: 資料類型 | C1: 內容/網址/文字 | D1: 真實標籤 | E1: 詐騙類型 | F1: 預期風險等級 | G1: 系統判斷 | H1: 系統分數 | I1: 是否判斷正確 | J1: 分析時間(秒) | K1: 高風險是否攔截 | L1: 家屬通知是否成功 | M1: 誤判類型 | N1: 資料來源 | O1: 測試日期 | P1: 測試人員 | Q1: 系統理由/備註
A2: T001 | B2: 詐騙簡訊 | C2: 衛生福利部通知：您已符合本年度長照2.0專案加碼資格，請立即點擊 [網址] 登錄 [姓名] 帳戶領取。 | D2: 詐騙 | E2: 假長照補助金 | F2: 高風險 | I2: =IF(G2="","",IF(AND(D2="詐騙",OR(G2="高風險",G2="中風險")),"是",IF(AND(D2="正常",G2="低風險"),"是","否"))) | M2: =IF(G2="","",IF(I2="是","",IF(AND(D2="詐騙",G2="低風險"),"漏判",IF(AND(D2="正常",OR(G2="中風險",G2="高風險")),"誤判","需檢查")))) | N2: 自製模擬 | O2: 2026-05-10
A3: T002 | B3: 詐騙簡訊 | C3: [姓名]長輩您好，您的長照補.助金50000元已核發，請加LINE [手機號碼] 聯繫專員提領。 | D3: 詐騙 | E3: 假長照補助金 | F3: 高風險 | I3: =IF(G3="","",IF(AND(D3="詐騙",OR(G3="高風險",G3="中風險")),"是",IF(AND(D3="正常",G3="低風險"),"是","否"))) | M3: =IF(G3="","",IF(I3="是","",IF(AND(D3="詐騙",G3="低風險"),"漏判",IF(AND(D3="正常",OR(G3="中風險",G3="高風險")),"誤判","需檢查")))) | N3: 自製模擬 | O3: 2026-05-10
A4: T003 | B4: 詐騙簡訊 | C4: 提醒您，第三季居家照護津貼尚未領取，請於今日內至 [網址] 確認您的銀行帳戶資料。 | D4: 詐騙 | E4: 假長照補助金 | F4: 高風險 | I4: =IF(G4="","",IF(AND(D4="詐騙",OR(G4="高風險",G4="中風險")),"是",IF(AND(D4="正常",G4="低風險"),"是","否"))) | M4: =IF(G4="","",IF(I4="是","",IF(AND(D4="詐騙",G4="低風險"),"漏判",IF(AND(D4="正常",OR(G4="中風險",G4="高風險")),"誤判","需檢查")))) | N4: 自製模擬 | O4: 2026-05-10
A5: T004 | B5: 詐騙簡訊 | C5: 健保局公告：因系統升級，您的長照補貼匯欵失敗，請速點 [網址] 重新綁定。 | D5: 詐騙 | E5: 假長照補助金 | F5: 高風險 | I5: =IF(G5="","",IF(AND(D5="詐騙",OR(G5="高風險",G5="中風險")),"是",IF(AND(D5="正常",G5="低風險"),"是","否"))) | M5: =IF(G5="","",IF(I5="是","",IF(AND(D5="詐騙",G5="低風險"),"漏判",IF(AND(D5="正常",OR(G5="中風險",G5="高風險")),"誤判","需檢查")))) | N5: 自製模擬 | O5: 2026-05-10
A6: T005 | B6: 詐騙簡訊 | C6: 【政府專案】恭喜獲得免費輪椅與每月8000元補助！請將身分證與存摺拍照發送至此號碼 [手機號碼]。 | D6: 詐騙 | E6: 假長照補助金 | F6: 高風險 | I6: =IF(G6="","",IF(AND(D6="詐騙",OR(G6="高風險",G6="中風險")),"是",IF(AND(D6="正常",G6="低風險"),"是","否"))) | M6: =IF(G6="","",IF(I6="是","",IF(AND(D6="詐騙",G6="低風險"),"漏判",IF(AND(D6="正常",OR(G6="中風險",G6="高風險")),"誤判","需檢查")))) | N6: 自製模擬 | O6: 2026-05-10
A7: T006 | B7: 詐騙簡訊 | C7: [姓名]先生/女士，您的長照居家服務時數可折現！請點擊 [網址] 填寫帳.戶進行提撥。 | D7: 詐騙 | E7: 假長照補助金 | F7: 高風險 | I7: =IF(G7="","",IF(AND(D7="詐騙",OR(G7="高風險",G7="中風險")),"是",IF(AND(D7="正常",G7="低風險"),"是","否"))) | M7: =IF(G7="","",IF(I7="是","",IF(AND(D7="詐騙",G7="低風險"),"漏判",IF(AND(D7="正常",OR(G7="中風險",G7="高風險")),"誤判","需檢查")))) | N7: 自製模擬 | O7: 2026-05-10
A8: T007 | B8: 詐騙簡訊 | C8: 社會局溫馨提示：您的敬老卡津貼發生異常，請聯絡 [手機號碼] 進行解鎖以利後續撥款。 | D8: 詐騙 | E8: 假長照補助金 | F8: 高風險 | I8: =IF(G8="","",IF(AND(D8="詐騙",OR(G8="高風險",G8="中風險")),"是",IF(AND(D8="正常",G8="低風險"),"是","否"))) | M8: =IF(G8="","",IF(I8="是","",IF(AND(D8="詐騙",G8="低風險"),"漏判",IF(AND(D8="正常",OR(G8="中風險",G8="高風險")),"誤判","需檢查")))) | N8: 自製模擬 | O8: 2026-05-10
A9: T008 | B9: 詐騙簡訊 | C9: 專屬老人津貼發放通知：金額已達上限，點擊 [網址] 快速入帳互，逾期視同放棄。 | D9: 詐騙 | E9: 假長照補助金 | F9: 高風險 | I9: =IF(G9="","",IF(AND(D9="詐騙",OR(G9="高風險",G9="中風險")),"是",IF(AND(D9="正常",G9="低風險"),"是","否"))) | M9: =IF(G9="","",IF(I9="是","",IF(AND(D9="詐騙",G9="低風險"),"漏判",IF(AND(D9="正常",OR(G9="中風險",G9="高風險")),"誤判","需檢查")))) | N9: 自製模擬 | O9: 2026-05-10
A10: T009 | B10: 詐騙簡訊 | C10: [姓名] 您好，您昨日於門診的批價系統發生重複扣款錯誤，請聯絡財務部 [手機號碼] 辦理退費。 | D10: 詐騙 | E10: 假醫院批價異常 | F10: 高風險 | I10: =IF(G10="","",IF(AND(D10="詐騙",OR(G10="高風險",G10="中風險")),"是",IF(AND(D10="正常",G10="低風險"),"是","否"))) | M10: =IF(G10="","",IF(I10="是","",IF(AND(D10="詐騙",G10="低風險"),"漏判",IF(AND(D10="正常",OR(G10="中風險",G10="高風險")),"誤判","需檢查")))) | N10: 自製模擬 | O10: 2026-05-10
A11: T010 | B11: 詐騙簡訊 | C11: 臺大醫院通知：您的醫藥費結帳異常，系統將每月自動扣款，請點擊 [網址] 立即取消設定。 | D11: 詐騙 | E11: 假醫院批價異常 | F11: 高風險 | I11: =IF(G11="","",IF(AND(D11="詐騙",OR(G11="高風險",G11="中風險")),"是",IF(AND(D11="正常",G11="低風險"),"是","否"))) | M11: =IF(G11="","",IF(I11="是","",IF(AND(D11="詐騙",G11="低風險"),"漏判",IF(AND(D11="正常",OR(G11="中風險",G11="高風險")),"誤判","需檢查")))) | N11: 自製模擬 | O11: 2026-05-10
A12: T011 | B12: 詐騙簡訊 | C12: 提醒：您的住院保證金50000元尚未退還，請提供 [姓名] 的提款卡密碼以利人工核對退款。 | D12: 詐騙 | E12: 假醫院批價異常 | F12: 高風險 | I12: =IF(G12="","",IF(AND(D12="詐騙",OR(G12="高風險",G12="中風險")),"是",IF(AND(D12="正常",G12="低風險"),"是","否"))) | M12: =IF(G12="","",IF(I12="是","",IF(AND(D12="詐騙",G12="低風險"),"漏判",IF(AND(D12="正常",OR(G12="中風險",G12="高風險")),"誤判","需檢查")))) | N12: 自製模擬 | O12: 2026-05-10
A13: T012 | B13: 詐騙簡訊 | C13: 批價處緊急通知：[姓名]的健保卡使用違規，即將鎖卡。請加LINE [手機號碼] 繳納罰金解除限制。 | D13: 詐騙 | E13: 假醫院批價異常 | F13: 高風險 | I13: =IF(G13="","",IF(AND(D13="詐騙",OR(G13="高風險",G13="中風險")),"是",IF(AND(D13="正常",G13="低風險"),"是","否"))) | M13: =IF(G13="","",IF(I13="是","",IF(AND(D13="詐騙",G13="低風險"),"漏判",IF(AND(D13="正常",OR(G13="中風險",G13="高風險")),"誤判","需檢查")))) | N13: 自製模擬 | O13: 2026-05-10
... A101: T100 | B101: 正常網站文字 | C101: 社會局長照科防詐騙提醒：辦理各項長照補助皆需透過官方正當管道，專員不會私下加LINE要求匯款或索取您的存摺密碼，切勿提供帳戶資訊給陌生人。 | D101: 正常 | E101: 無 | F101: 低風險 | I101: =IF(G101="","",IF(AND(D101="詐騙",OR(G101="高風險",G101="中風險")),"是",IF(AND(D101="正常",G101="低風險"),"是","否"))) | M101: =IF(G101="","",IF(I101="是","",IF(AND(D101="詐騙",G101="低風險"),"漏判",IF(AND(D101="正常",OR(G101="中風險",G101="高風險")),"誤判","需檢查")))) | N101: 自製模擬 | O101: 2026-05-10

Sheet 統計儀表板
A1: AI 防詐盾牌｜高齡情境測試資料集統計儀表板
A3: 指標 | B3: 公式/結果 | C3: 說明 | E3: 資料類型 | F3: 筆數
A4: 測試總數 | B4: =COUNTA(測試資料集!A2:A101) -> 100 | C4: 資料集總筆數 | E4: 詐騙簡訊 | F4: =COUNTIF(測試資料集!B2:B101,"詐騙簡訊") -> 30
A5: 詐騙樣本 | B5: =COUNTIF(測試資料集!D2:D101,"詐騙") -> 50 | C5: 真實標籤為詐騙 | E5: 詐騙網站文字 | F5: =COUNTIF(測試資料集!B2:B101,"詐騙網站文字") -> 20
A6: 正常樣本 | B6: =COUNTIF(測試資料集!D2:D101,"正常") -> 50 | C6: 真實標籤為正常 | E6: 正常通知訊息 | F6: =COUNTIF(測試資料集!B2:B101,"正常通知訊息") -> 30
A7: 已完成系統判斷 | B7: =COUNTIF(測試資料集!G2:G101,"<>") -> 0 | C7: 已填入系統判斷的筆數 | E7: 正常網站文字 | F7: =COUNTIF(測試資料集!B2:B101,"正常網站文字") -> 20
A8: 整體正確率 | B8: =IFERROR(COUNTIF(測試資料集!I2:I101,"是")/COUNTIF(測試資料集!G2:G101,"<>"),"尚未測試") -> 尚未測試 | C8: 完成測試後自動計算
A9: 詐騙辨識率 | B9: =IFERROR(COUNTIFS(測試資料集!D2:D101,"詐騙",測試資料集!I2:I101,"是")/COUNTIF(測試資料集!D2:D101,"詐騙"),"尚未測試") -> 0 | C9: 詐騙被判為高/中風險
A10: 正常誤判率 | B10: =IFERROR(COUNTIFS(測試資料集!D2:D101,"正常",測試資料集!I2:I101,"否")/COUNTIF(測試資料集!D2:D101,"正常"),"尚未測試") -> 0 | C10: 正常被判成中/高風險
A11: 平均分析時間 | B11: =IFERROR(AVERAGE(測試資料集!J2:J101),"尚未測試") -> 尚未測試 | C11: 單位：秒
A14: 詐騙類型 | B14: 筆數 | D14: 使用說明
A15: 假投資 / 保證獲利 | B15: =COUNTIF(測試資料集!E2:E101,"假投資 / 保證獲利") -> 5 | D15: 1. 在「測試資料集」填入系統判斷、系統分數、分析時間。
A16: 假檢警 / 帳戶凍結 | B16: =COUNTIF(測試資料集!E2:E101,"假檢警 / 帳戶凍結") -> 3 | D16: 2. 「是否判斷正確」與「誤判類型」已有公式，會自動判斷。
A17: 假物流 / 包裹補繳運費 | B17: =COUNTIF(測試資料集!E2:E101,"假物流 / 包裹補繳運費") -> 6 | D17: 3. 完成測試後，統計儀表板會自動更新整體正確率、詐騙辨識率與正常誤判率。
A18: 假網購特效保健食品 | B18: =COUNTIF(測試資料集!E2:E101,"假網購特效保健食品") -> 8 | D18: 4. 正常防詐宣導文字含有詐騙關鍵字，是用來測試系統是否過度誤判。
A19: 假親友借醫療費 | B19: =COUNTIF(測試資料集!E2:E101,"假親友借醫療費") -> 8 | D19: 5. 部分詐騙樣本刻意加入錯字、插點與同音字，用來測試變形話術辨識能力。
A20: 假醫院批價異常 | B20: =COUNTIF(測試資料集!E2:E101,"假醫院批價異常") -> 8
A21: 假銀行 / 釣魚登入 | B21: =COUNTIF(測試資料集!E2:E101,"假銀行 / 釣魚登入") -> 4
A22: 假長照補助金 | B22: =COUNTIF(測試資料集!E2:E101,"假長照補助金") -> 8

Sheet 欄位說明
A1: 欄位 | B1: 填寫方式 | C1: 備註
A2: 編號 | B2: T001～T100 | C2: 唯一識別碼，不建議修改
A3: 資料類型 | B3: 詐騙簡訊 / 詐騙網站文字 / 正常通知訊息 / 正常網站文字 | C3: 用於分類統計
A4: 內容/網址/文字 | B4: 放入測試訊息或網頁文字 | C4: 已用 [網址]、[姓名]、[手機號碼] 遮蔽個資
A5: 真實標籤 | B5: 詐騙 / 正常 | C5: 人工標註的標準答案
A6: 詐騙類型 | B6: 假長照補助金、假醫院批價異常等 | C6: 正常資料填「無」
A7: 預期風險等級 | B7: 高風險 / 低風險 | C7: 詐騙樣本預期高風險，正常樣本預期低風險
A8: 系統判斷 | B8: 高風險 / 中風險 / 低風險 | C8: 跑完 AI 防詐盾牌後填入
A9: 系統分數 | B9: 0～100 | C9: 系統回傳風險分數
A10: 是否判斷正確 | B10: 自動公式 | C10: 詐騙判高/中風險算正確；正常判低風險算正確
A11: 分析時間(秒) | B11: 填入秒數，例如 1.23 | C11: 用於計算平均分析時間
A12: 高風險是否攔截 | B12: 成功 / 失敗 / 不適用 / 未測 | C12: 高風險測試時填寫
... A18: 系統理由/備註 | B18: 填入系統回傳理由或人工備註 | C18: 可記錄誤判原因
